[
        {

            "id": 1,
            "name": "H"

        },
        {

            "id": 2,
            "name": "He"


        },
        {

            "id": 3,
            "name": "Li"

        },
        {

            "id": 4,
            "name": "Be"

        },
        {

            "id": 5,
            "name": "B"

        },
        {
            "id": 6,
            "name": "C"

        },
        {
            "id": 7,
            "name": "N"

        },
        {
            "id": 8,
            "name": "O"

        },
        {
            "id": 9,
            "name": "F"

        },
        {
            "id": 10,
            "name": "Ne"

        },
        {
            "id": 11,
            "name": "Na"

        },
        {
            "id": 12,
            "name": "Mg"

        },
        {
            "id": 13,
            "name": "Al"

        },
        {
            "id": 14,
            "name": "Si"

        },
        {
            "id": 15,
            "name": "P"

        },
        {
            "id": 16,
            "name": "S"

        },
        {
            "id": 17,
            "name": "Cl"

        },
        {
            "id": 18,
            "name": "Ar"

        },
        {
            "id": 19,
            "name": "K"

        },
        {
            "id": 20,
            "name": "Ca"

        },
        {
            "id": 21,
            "name": "Sc"

        },
        {
            "id": 22,
            "name": "Ti"

        },
        {
            "id": 23,
            "name": "V"

        },
        {
            "id": 24,
            "name": "Cr"

        },
        {
            "id": 25,
            "name": "Mn"

        },
        {
            "id": 26,
            "name": "Fe"

        },
        {
            "id": 27,
            "name": "Co"

        },
        {
            "id": 28,
            "name": "Ni"
                    },
        {
            "id": 29,
            "name": "Cu"

        },
        {
            "id": 30,
            "name": "Zn"

        },
        {
            "id": 31,
            "name": "Ga"

        },
        {
            "id": 32,
            "name": "Ge"

        },
        {
            "id": 33,
            "name": "As"

        },
        {
            "id": 34,
            "name": "Se"

        },
        {
            "id": 35,
            "name": "Br"

        },
        {
            "id": 36,
            "name": "Kr"

        },
        {
            "id": 37,
            "name": "Rb"

        },
        {
            "id": 38,
            "name": "Sr"

        },
        {
            "id": 39,
            "name": "Y"

        },
        {
            "id": 40,
            "name": "Zr"

        },
        {
            "id": 41,
            "name": "Nb"

        },
        {
            "id": 42,
            "name": "Mo"

        },
        {
            "id": 43,
            "name": "Tc"

        }
  ]